factorial/__init__.py
factorial/agent.py
factorial/context.py
factorial/events.py
factorial/exceptions.py
factorial/llms.py
factorial/logging.py
factorial/orchestrator.py
factorial/tools.py
factorial/utils.py
factorial/dashboard/__init__.py
factorial/dashboard/dashboard.html
factorial/dashboard/dashboard.js
factorial/dashboard/routes.py
factorial/dashboard/assets/factorial-logo.ico
factorial/queue/__init__.py
factorial/queue/keys.py
factorial/queue/maintenance.py
factorial/queue/operations.py
factorial/queue/task.py
factorial/queue/worker.py
factorial/queue/lua/__init__.py
factorial/queue/lua/_loader.py
factorial/queue/lua/backoff.lua
factorial/queue/lua/cancellation.lua
factorial/queue/lua/child_completion.lua
factorial/queue/lua/completion.lua
factorial/queue/lua/enqueue.lua
factorial/queue/lua/enqueue_batch.lua
factorial/queue/lua/expiration.lua
factorial/queue/lua/pickup.lua
factorial/queue/lua/recovery.lua
factorial/queue/lua/shared.lua
factorial/queue/lua/steering.lua
factorial/queue/lua/tool_completion.lua
nfactorial-0.1.30.dist-info/METADATA
nfactorial-0.1.30.dist-info/WHEEL
nfactorial-0.1.30.dist-info/top_level.txt
nfactorial-0.1.30.dist-info/RECORD
