Metadata-Version: 2.4
Name: nfactorial
Version: 0.1.30
Summary: A distributed task queue for building reliable multi-agent systems.
Project-URL: Homepage, https://factorial.sh
Project-URL: Repository, https://github.com/ricardo-agz/nfactorial
Project-URL: Documentation, https://factorial.sh
Project-URL: Issues, https://github.com/ricardo-agz/nfactorial/issues
Classifier: Typing :: Typed
Classifier: Development Status :: 3 - Alpha
Classifier: Intended Audience :: Developers
Classifier: Topic :: Software Development :: Libraries :: Python Modules
Classifier: License :: OSI Approved :: MIT License
Classifier: Programming Language :: Python :: 3
Classifier: Programming Language :: Python :: 3.9
Classifier: Programming Language :: Python :: 3.10
Classifier: Programming Language :: Python :: 3.11
Classifier: Programming Language :: Python :: 3.12
Requires-Python: >=3.9
Requires-Dist: python-dotenv>=1.0.0
Requires-Dist: openai>=1.81.0
Requires-Dist: pydantic<3,>=2.10
Requires-Dist: redis>=6.1.0
Requires-Dist: fastapi<1,>=0.110.0
Requires-Dist: uvicorn[standard]>=0.34.2
Requires-Dist: websockets>=15.0.1
Provides-Extra: dev
Requires-Dist: mypy; extra == "dev"
Requires-Dist: pytest; extra == "dev"
Requires-Dist: pytest-asyncio; extra == "dev"
Requires-Dist: black; extra == "dev"
Requires-Dist: isort>=5.12.0; extra == "dev"
Requires-Dist: flake8>=6.0.0; extra == "dev"
